autotrader_scraper/__init__.py
autotrader_scraper/scraper.py
autotrader_scraper-0.1.1.dist-info/LICENSE
autotrader_scraper-0.1.1.dist-info/METADATA
autotrader_scraper-0.1.1.dist-info/WHEEL
autotrader_scraper-0.1.1.dist-info/top_level.txt
autotrader_scraper-0.1.1.dist-info/RECORD
