Metadata-Version: 2.1
Name: autotrader-scraper
Version: 0.1.1
Summary: Scraper for AutoTrader.co.uk
Home-page: https://github.com/suhailidrees/autotrader_scraper
Author: Suhail Idrees
Author-email: idrees.suhail@gmail.com
License: UNKNOWN
Platform: UNKNOWN
Classifier: Programming Language :: Python :: 3
Classifier: License :: OSI Approved :: MIT License
Classifier: Operating System :: OS Independent
Requires-Python: >=3.0
